PyQt6/Qt3DAnimation.abi3.so
PyQt6/Qt3DAnimation.pyi
PyQt6/Qt3DCore.abi3.so
PyQt6/Qt3DCore.pyi
PyQt6/Qt3DExtras.abi3.so
PyQt6/Qt3DExtras.pyi
PyQt6/Qt3DInput.abi3.so
PyQt6/Qt3DInput.pyi
PyQt6/Qt3DLogic.abi3.so
PyQt6/Qt3DLogic.pyi
PyQt6/Qt3DRender.abi3.so
PyQt6/Qt3DRender.pyi
PyQt6/Qt6/qsci/api/python/PyQt6-3D.api
PyQt6/bindings/Qt3DAnimation/Qt3DAnimation.toml
PyQt6/bindings/Qt3DAnimation/Qt3DAnimationmod.sip
PyQt6/bindings/Qt3DAnimation/qabstractanimation.sip
PyQt6/bindings/Qt3DAnimation/qabstractanimationclip.sip
PyQt6/bindings/Qt3DAnimation/qabstractchannelmapping.sip
PyQt6/bindings/Qt3DAnimation/qabstractclipanimator.sip
PyQt6/bindings/Qt3DAnimation/qabstractclipblendnode.sip
PyQt6/bindings/Qt3DAnimation/qadditiveclipblend.sip
PyQt6/bindings/Qt3DAnimation/qanimationaspect.sip
PyQt6/bindings/Qt3DAnimation/qanimationclip.sip
PyQt6/bindings/Qt3DAnimation/qanimationclipdata.sip
PyQt6/bindings/Qt3DAnimation/qanimationcliploader.sip
PyQt6/bindings/Qt3DAnimation/qanimationcontroller.sip
PyQt6/bindings/Qt3DAnimation/qanimationgroup.sip
PyQt6/bindings/Qt3DAnimation/qblendedclipanimator.sip
PyQt6/bindings/Qt3DAnimation/qchannel.sip
PyQt6/bindings/Qt3DAnimation/qchannelcomponent.sip
PyQt6/bindings/Qt3DAnimation/qchannelmapper.sip
PyQt6/bindings/Qt3DAnimation/qchannelmapping.sip
PyQt6/bindings/Qt3DAnimation/qclipanimator.sip
PyQt6/bindings/Qt3DAnimation/qclipblendvalue.sip
PyQt6/bindings/Qt3DAnimation/qclock.sip
PyQt6/bindings/Qt3DAnimation/qkeyframe.sip
PyQt6/bindings/Qt3DAnimation/qkeyframeanimation.sip
PyQt6/bindings/Qt3DAnimation/qlerpclipblend.sip
PyQt6/bindings/Qt3DAnimation/qmorphinganimation.sip
PyQt6/bindings/Qt3DAnimation/qmorphtarget.sip
PyQt6/bindings/Qt3DAnimation/qskeletonmapping.sip
PyQt6/bindings/Qt3DAnimation/qvertexblendanimation.sip
PyQt6/bindings/Qt3DCore/Qt3DCore.toml
PyQt6/bindings/Qt3DCore/Qt3DCoremod.sip
PyQt6/bindings/Qt3DCore/qabstractaspect.sip
PyQt6/bindings/Qt3DCore/qabstractfunctor.sip
PyQt6/bindings/Qt3DCore/qabstractskeleton.sip
pyqt6_3d-6.10.0.dist-info/licenses/LICENSE
pyqt6_3d-6.10.0.dist-info/WHEEL
pyqt6_3d-6.10.0.dist-info/METADATA
pyqt6_3d-6.10.0.dist-info/RECORD
