Metadata-Version: 2.4
Name: PyQt6-3D
Version: 6.10.0
Requires-Python: >=3.9
Summary: Python bindings for the Qt 3D framework
Project-Url: homepage, https://www.riverbankcomputing.com/software/pyqt3d/
Requires-Dist: PyQt6-sip (>=13.8, <14)
Requires-Dist: PyQt6-3D-Qt6 (>=6.10.0, <6.11.0)
Requires-Dist: PyQt6 (>=6.2.0)
License-Expression: GPL-3.0-only
License-File: LICENSE
Author-Email: Riverbank Computing Limited <info@riverbankcomputing.com>
